simple_log/__init__.py
simple_log/log_utilities.py
simple_log-0.0.4.dist-info/LICENSE.md
simple_log-0.0.4.dist-info/METADATA
simple_log-0.0.4.dist-info/WHEEL
simple_log-0.0.4.dist-info/dependency_links.txt
simple_log-0.0.4.dist-info/top_level.txt
simple_log-0.0.4.dist-info/RECORD
