Metadata-Version: 2.1
Name: simple-log
Version: 0.0.4
Summary: A python module with sensible defaults for logging
Home-page: https://hg.sr.ht/~andy47/simple_log
Author: Andy Todd
Author-email: andy47@halfcooked.com
License: MIT
Classifier: Development Status :: 3 - Alpha
Classifier: Intended Audience :: Developers
Classifier: Programming Language :: Python :: 3
License-File: LICENSE.md
